pybush.py
pybush-1.1.0.dist-info/METADATA
pybush-1.1.0.dist-info/WHEEL
pybush-1.1.0.dist-info/top_level.txt
pybush-1.1.0.dist-info/RECORD
