Metadata-Version: 2.1
Name: pybush
Version: 1.1.0
Summary: python implementation of avl,bbst,bst and more
Home-page: https://github.com/nikhil0360
Author: nikhil agarwal
Author-email: nikhil.agarwal@iiitb.org
License: UNKNOWN
Download-URL: https://github.com/nikhil0360/pybush/archive/v1.1.0.tar.gz
Platform: UNKNOWN
Requires-Dist: binarytree
